bigslacker.py
bigslacker-0.1.1.dist-info/DESCRIPTION.rst
bigslacker-0.1.1.dist-info/METADATA
bigslacker-0.1.1.dist-info/RECORD
bigslacker-0.1.1.dist-info/WHEEL
bigslacker-0.1.1.dist-info/metadata.json
bigslacker-0.1.1.dist-info/top_level.txt
