Metadata-Version: 2.0
Name: bigslacker
Version: 0.1.1
Summary: Slack RTM Client
Home-page: https://github.com/nicholasamorim/bigslacker
Author: Nicholas Amorim
Author-email: nicholas@alienretro.com
License: GPL
Keywords: api consumer client slack chat real time
Platform: UNKNOWN
Classifier: Development Status :: 3 - Alpha
Classifier: Operating System :: POSIX :: Linux
Classifier: Environment :: Console
Classifier: Intended Audience :: Developers
Classifier: License :: OSI Approved :: GNU General Public License v3 (GPLv3)
Classifier: Topic :: Communications :: Chat
Classifier: Programming Language :: Python
Classifier: Programming Language :: Python :: 2
Classifier: Programming Language :: Python :: 2.7
Classifier: Programming Language :: Python :: 3
Classifier: Programming Language :: Python :: 3.4
Requires-Dist: slackclient
